nmme/__init__.py
nmme-0.5.data/scripts/nmme-test
nmme-0.5.dist-info/METADATA
nmme-0.5.dist-info/WHEEL
nmme-0.5.dist-info/top_level.txt
nmme-0.5.dist-info/RECORD
